[
  {"id": 1548, "coherent": true, "failure_mode": null},
  {"id": 1549, "coherent": true, "failure_mode": null},
  {"id": 1550, "coherent": true, "failure_mode": null},
  {"id": 1551, "coherent": true, "failure_mode": null},
  {"id": 1552, "coherent": true, "failure_mode": null},
  {"id": 1553, "coherent": true, "failure_mode": null},
  {"id": 1554, "coherent": true, "failure_mode": null},
  {"id": 1555, "coherent": true, "failure_mode": null},
  {"id": 1556, "coherent": true, "failure_mode": null},
  {"id": 1557, "coherent": true, "failure_mode": null},
  {"id": 1558, "coherent": true, "failure_mode": null},
  {"id": 1559, "coherent": true, "failure_mode": null},
  {"id": 1560, "coherent": true, "failure_mode": null},
  {"id": 1561, "coherent": true, "failure_mode": null},
  {"id": 1562, "coherent": true, "failure_mode": null},
  {"id": 1563, "coherent": true, "failure_mode": null},
  {"id": 1564, "coherent": true, "failure_mode": null},
  {"id": 1565, "coherent": false, "failure_mode": "word_repetition"},
  {"id": 1566, "coherent": true, "failure_mode": null},
  {"id": 1567, "coherent": false, "failure_mode": "word_salad"},
  {"id": 1568, "coherent": true, "failure_mode": null},
  {"id": 1569, "coherent": true, "failure_mode": null},
  {"id": 1570, "coherent": true, "failure_mode": null},
  {"id": 1571, "coherent": true, "failure_mode": null},
  {"id": 1572, "coherent": true, "failure_mode": null},
  {"id": 1573, "coherent": true, "failure_mode": null},
  {"id": 1574, "coherent": true, "failure_mode": null},
  {"id": 1575, "coherent": true, "failure_mode": null},
  {"id": 1576, "coherent": true, "failure_mode": null},
  {"id": 1577, "coherent": true, "failure_mode": null},
  {"id": 1578, "coherent": true, "failure_mode": null},
  {"id": 1579, "coherent": true, "failure_mode": null},
  {"id": 1580, "coherent": false, "failure_mode": "word_repetition"},
  {"id": 1581, "coherent": true, "failure_mode": null},
  {"id": 1582, "coherent": false, "failure_mode": "off_topic"},
  {"id": 1583, "coherent": true, "failure_mode": null},
  {"id": 1584, "coherent": false, "failure_mode": "fragmented"},
  {"id": 1585, "coherent": false, "failure_mode": "token_repetition"},
  {"id": 1586, "coherent": true, "failure_mode": null},
  {"id": 1587, "coherent": false, "failure_mode": "fragmented"},
  {"id": 1588, "coherent": false, "failure_mode": "fragmented"},
  {"id": 1589, "coherent": false, "failure_mode": "fragmented"},
  {"id": 1590, "coherent": false, "failure_mode": "word_salad"},
  {"id": 1591, "coherent": true, "failure_mode": null},
  {"id": 1592, "coherent": false, "failure_mode": "fragmented"},
  {"id": 1593, "coherent": false, "failure_mode": "fragmented"},
  {"id": 1594, "coherent": false, "failure_mode": "corrupted_tokens"},
  {"id": 1595, "coherent": true, "failure_mode": null},
  {"id": 1596, "coherent": true, "failure_mode": null},
  {"id": 1597, "coherent": true, "failure_mode": null},
  {"id": 1598, "coherent": true, "failure_mode": null},
  {"id": 1599, "coherent": true, "failure_mode": null},
  {"id": 1600, "coherent": true, "failure_mode": null},
  {"id": 1601, "coherent": true, "failure_mode": null},
  {"id": 1602, "coherent": true, "failure_mode": null},
  {"id": 1603, "coherent": false, "failure_mode": "empty"},
  {"id": 1604, "coherent": false, "failure_mode": "word_salad"},
  {"id": 1605, "coherent": true, "failure_mode": null},
  {"id": 1606, "coherent": true, "failure_mode": null},
  {"id": 1607, "coherent": true, "failure_mode": null},
  {"id": 1608, "coherent": false, "failure_mode": "corrupted_tokens"},
  {"id": 1609, "coherent": true, "failure_mode": null},
  {"id": 1610, "coherent": true, "failure_mode": null},
  {"id": 1611, "coherent": false, "failure_mode": "fragmented"},
  {"id": 1612, "coherent": true, "failure_mode": null},
  {"id": 1613, "coherent": false, "failure_mode": "corrupted_tokens"},
  {"id": 1614, "coherent": false, "failure_mode": "fragmented"},
  {"id": 1615, "coherent": true, "failure_mode": null},
  {"id": 1616, "coherent": false, "failure_mode": "token_repetition"},
  {"id": 1617, "coherent": true, "failure_mode": null},
  {"id": 1618, "coherent": false, "failure_mode": "fragmented"},
  {"id": 1619, "coherent": false, "failure_mode": "fragmented"},
  {"id": 1440, "coherent": true, "failure_mode": null},
  {"id": 1441, "coherent": true, "failure_mode": null},
  {"id": 1442, "coherent": true, "failure_mode": null},
  {"id": 1443, "coherent": true, "failure_mode": null},
  {"id": 1444, "coherent": true, "failure_mode": null},
  {"id": 1445, "coherent": true, "failure_mode": null},
  {"id": 1446, "coherent": true, "failure_mode": null},
  {"id": 1447, "coherent": true, "failure_mode": null},
  {"id": 1448, "coherent": true, "failure_mode": null},
  {"id": 1449, "coherent": true, "failure_mode": null},
  {"id": 1450, "coherent": true, "failure_mode": null},
  {"id": 1451, "coherent": true, "failure_mode": null},
  {"id": 1452, "coherent": true, "failure_mode": null},
  {"id": 1453, "coherent": true, "failure_mode": null},
  {"id": 1454, "coherent": true, "failure_mode": null},
  {"id": 1455, "coherent": true, "failure_mode": null},
  {"id": 1456, "coherent": true, "failure_mode": null},
  {"id": 1457, "coherent": true, "failure_mode": null},
  {"id": 1458, "coherent": true, "failure_mode": null},
  {"id": 1459, "coherent": true, "failure_mode": null},
  {"id": 1460, "coherent": true, "failure_mode": null},
  {"id": 1461, "coherent": true, "failure_mode": null},
  {"id": 1462, "coherent": true, "failure_mode": null},
  {"id": 1463, "coherent": true, "failure_mode": null},
  {"id": 1464, "coherent": true, "failure_mode": null},
  {"id": 1465, "coherent": true, "failure_mode": null},
  {"id": 1466, "coherent": true, "failure_mode": null},
  {"id": 1467, "coherent": true, "failure_mode": null},
  {"id": 1468, "coherent": true, "failure_mode": null},
  {"id": 1469, "coherent": true, "failure_mode": null},
  {"id": 1470, "coherent": true, "failure_mode": null},
  {"id": 1471, "coherent": true, "failure_mode": null},
  {"id": 1472, "coherent": true, "failure_mode": null},
  {"id": 1473, "coherent": true, "failure_mode": null},
  {"id": 1474, "coherent": true, "failure_mode": null},
  {"id": 1475, "coherent": true, "failure_mode": null},
  {"id": 1476, "coherent": true, "failure_mode": null},
  {"id": 1477, "coherent": true, "failure_mode": null},
  {"id": 1478, "coherent": true, "failure_mode": null},
  {"id": 1479, "coherent": true, "failure_mode": null},
  {"id": 1480, "coherent": true, "failure_mode": null},
  {"id": 1481, "coherent": true, "failure_mode": null},
  {"id": 1482, "coherent": true, "failure_mode": null},
  {"id": 1483, "coherent": true, "failure_mode": null},
  {"id": 1484, "coherent": true, "failure_mode": null},
  {"id": 1485, "coherent": true, "failure_mode": null},
  {"id": 1486, "coherent": true, "failure_mode": null},
  {"id": 1487, "coherent": true, "failure_mode": null},
  {"id": 1488, "coherent": true, "failure_mode": null},
  {"id": 1489, "coherent": true, "failure_mode": null},
  {"id": 1490, "coherent": true, "failure_mode": null},
  {"id": 1491, "coherent": true, "failure_mode": null},
  {"id": 1492, "coherent": true, "failure_mode": null},
  {"id": 1493, "coherent": true, "failure_mode": null},
  {"id": 1494, "coherent": true, "failure_mode": null},
  {"id": 1495, "coherent": true, "failure_mode": null},
  {"id": 1496, "coherent": true, "failure_mode": null},
  {"id": 1497, "coherent": true, "failure_mode": null},
  {"id": 1498, "coherent": true, "failure_mode": null},
  {"id": 1499, "coherent": true, "failure_mode": null},
  {"id": 1500, "coherent": true, "failure_mode": null},
  {"id": 1501, "coherent": true, "failure_mode": null},
  {"id": 1502, "coherent": true, "failure_mode": null},
  {"id": 1503, "coherent": true, "failure_mode": null},
  {"id": 1504, "coherent": true, "failure_mode": null},
  {"id": 1505, "coherent": true, "failure_mode": null},
  {"id": 1506, "coherent": true, "failure_mode": null},
  {"id": 1507, "coherent": true, "failure_mode": null},
  {"id": 1508, "coherent": true, "failure_mode": null},
  {"id": 1509, "coherent": true, "failure_mode": null},
  {"id": 1510, "coherent": true, "failure_mode": null},
  {"id": 1511, "coherent": true, "failure_mode": null},
  {"id": 1512, "coherent": true, "failure_mode": null},
  {"id": 1513, "coherent": true, "failure_mode": null},
  {"id": 1514, "coherent": true, "failure_mode": null},
  {"id": 1515, "coherent": true, "failure_mode": null},
  {"id": 1516, "coherent": true, "failure_mode": null},
  {"id": 1517, "coherent": true, "failure_mode": null},
  {"id": 1518, "coherent": true, "failure_mode": null},
  {"id": 1519, "coherent": true, "failure_mode": null},
  {"id": 1520, "coherent": true, "failure_mode": null},
  {"id": 1521, "coherent": true, "failure_mode": null},
  {"id": 1522, "coherent": true, "failure_mode": null},
  {"id": 1523, "coherent": true, "failure_mode": null},
  {"id": 1524, "coherent": true, "failure_mode": null},
  {"id": 1525, "coherent": true, "failure_mode": null},
  {"id": 1526, "coherent": true, "failure_mode": null},
  {"id": 1527, "coherent": true, "failure_mode": null},
  {"id": 1528, "coherent": true, "failure_mode": null},
  {"id": 1529, "coherent": true, "failure_mode": null},
  {"id": 1530, "coherent": true, "failure_mode": null},
  {"id": 1531, "coherent": true, "failure_mode": null},
  {"id": 1532, "coherent": true, "failure_mode": null},
  {"id": 1533, "coherent": true, "failure_mode": null},
  {"id": 1534, "coherent": true, "failure_mode": null},
  {"id": 1535, "coherent": true, "failure_mode": null},
  {"id": 1536, "coherent": true, "failure_mode": null},
  {"id": 1537, "coherent": true, "failure_mode": null},
  {"id": 1538, "coherent": true, "failure_mode": null},
  {"id": 1539, "coherent": true, "failure_mode": null},
  {"id": 1540, "coherent": true, "failure_mode": null},
  {"id": 1541, "coherent": true, "failure_mode": null},
  {"id": 1542, "coherent": true, "failure_mode": null},
  {"id": 1543, "coherent": true, "failure_mode": null},
  {"id": 1544, "coherent": true, "failure_mode": null},
  {"id": 1545, "coherent": true, "failure_mode": null},
  {"id": 1546, "coherent": true, "failure_mode": null},
  {"id": 1547, "coherent": true, "failure_mode": null}
]
